<?xml version="1.0" encoding="UTF-8"?>
<objects serializationModel="Studio.02.02.00">
	<object class="AudioFile" id="{c8a169cb-8fa6-471f-90e3-2e3ee60c55b9}">
		<property name="assetPath">
			<value>SFX/Cats/Cat_Place/Materials/Dumpster/Cat_Place_Dumpster_02.wav</value>
		</property>
		<property name="frequencyInKHz">
			<value>44.0999985</value>
		</property>
		<property name="channelCount">
			<value>2</value>
		</property>
		<property name="length">
			<value>1.0614285714285714</value>
		</property>
		<relationship name="masterAssetFolder">
			<destination>{e262c25e-1e1a-4a97-a512-e60b0c073004}</destination>
		</relationship>
	</object>
</objects>
